__init__.py
_apex_code_main.py
apex_code/__init__.py
apex_code/ai/__init__.py
apex_code/ai/neural_networks/__init__.py
apex_code/ai/neural_networks/activations.py
apex_code/ai/neural_networks/feed_forward.py
apex_code/math/__init__.py
apex_code/math/constants.py
apex_code/math/linear_algebra/__init__.py
apex_code/math/linear_algebra/matrix.py
apex_code/utils/__init__.py
apex_code/utils/random.py
apex_code-2.0.0.dist-info/LICENSE
apex_code-2.0.0.dist-info/METADATA
apex_code-2.0.0.dist-info/WHEEL
apex_code-2.0.0.dist-info/top_level.txt
apex_code-2.0.0.dist-info/RECORD
