Metadata-Version: 2.1
Name: apex_code
Version: 2.0.0
Summary: Swiss army knife personal code library
Author-email: Byron Farrell <byronfarrell22@gmail.com>
Project-URL: Homepage, https://github.com/Byron-Farrell/Matrix
Project-URL: Issues, https://github.com/Byron-Farrell/Matrix/issues
Classifier: Programming Language :: Python :: 3
Classifier: License :: OSI Approved :: MIT License
Classifier: Operating System :: OS Independent
Requires-Python: >=3.8
License-File: LICENSE
